greyhorse_core/__init__.py
greyhorse_core/app/__init__.py
greyhorse_core/app/application.py
greyhorse_core/app/base.py
greyhorse_core/app/context.py
greyhorse_core/app/module.py
greyhorse_core/app/service.py
greyhorse_core/app/visitors.py
greyhorse_core/data/__init__.py
greyhorse_core/data/cache/__init__.py
greyhorse_core/data/cache/base.py
greyhorse_core/data/cache/method.py
greyhorse_core/data/models/__init__.py
greyhorse_core/data/models/base.py
greyhorse_core/data/models/fields.py
greyhorse_core/data/models/filterable.py
greyhorse_core/data/models/model.py
greyhorse_core/data/models/serializable.py
greyhorse_core/data/repositories/__init__.py
greyhorse_core/data/repositories/base.py
greyhorse_core/data/repositories/filterable.py
greyhorse_core/data/serializers/__init__.py
greyhorse_core/data/serializers/base.py
greyhorse_core/data/serializers/pickle.py
greyhorse_core/engines/__init__.py
greyhorse_core/engines/base.py
greyhorse_core/engines/factory.py
greyhorse_core/i18n/__init__.py
greyhorse_core/i18n/translator.py
greyhorse_core/logging.py
greyhorse_core/messagebus.py
greyhorse_core/result.py
greyhorse_core/utils/__init__.py
greyhorse_core/utils/confs.py
greyhorse_core/utils/dicts.py
greyhorse_core/utils/hashes.py
greyhorse_core/utils/imports.py
greyhorse_core/utils/invoke.py
greyhorse_core/utils/json.py
greyhorse_core/utils/strings.py
greyhorse_core/utils/time.py
greyhorse_core-0.3.dist-info/METADATA
greyhorse_core-0.3.dist-info/WHEEL
greyhorse_core-0.3.dist-info/RECORD
