Metadata-Version: 2.1
Name: greyhorse-core
Version: 0.3
Summary: Greyhorse Core library
Home-page: https://gitlab.com/max-plutonium/greyhorse
License: MIT
Author: Max Plutonium
Author-email: plutonium.max@gmail.com
Maintainer: Max Plutonium
Maintainer-email: plutonium.max@gmail.com
Requires-Python: >=3.11,<4.0
Classifier: License :: OSI Approved :: MIT License
Classifier: Programming Language :: Python :: 3
Classifier: Programming Language :: Python :: 3.11
Classifier: Programming Language :: Python :: 3
Classifier: Programming Language :: Python :: 3.11
Requires-Dist: asyncclick (>=8.1.3,<9.0.0)
Requires-Dist: click (>=8.1.3,<9.0.0)
Requires-Dist: dependency-injector[pydantic] (>=4.41,<5.0)
Requires-Dist: orjson (>=3.8,<4.0)
Requires-Dist: pydantic[dotenv,email] (>=1.10,<2.0)
Requires-Dist: pytz (>=2022.7,<2023.0)
Requires-Dist: timeparse-plus (>=1.2,<2.0)
Requires-Dist: tomlkit (>=0.11,<0.12)
Project-URL: Repository, https://gitlab.com/max-plutonium/greyhorse
